miditapyr/__init__.py
miditapyr/midi_frame.py
miditapyr/mido_io.py
miditapyr/data/test_midi_file.mid
miditapyr-0.1.1.dist-info/LICENSE
miditapyr-0.1.1.dist-info/METADATA
miditapyr-0.1.1.dist-info/WHEEL
miditapyr-0.1.1.dist-info/top_level.txt
miditapyr-0.1.1.dist-info/RECORD
