Metadata-Version: 2.1
Name: miditapyr
Version: 0.1.1
Summary: Tabulate midi data in DataFrames and write back to midi files
Home-page: https://github.com/urswilke/miditapyr/
Author: Urs Wilke
Author-email: urs.wilke@gmail.com
License: MIT
Platform: UNKNOWN
License-File: LICENSE
